{
"type": "FeatureCollection",
"name": "pts",
"crs": { "type": "name", "properties": { "name": "urn:ogc:def:crs:OGC:1.3:CRS84" } },
"features": [
{ "type": "Feature", "properties": { }, "geometry": { "type": "Point", "coordinates": [ 1.739962099255797, 50.256401255932275 ] } },
{ "type": "Feature", "properties": { }, "geometry": { "type": "Point", "coordinates": [ 1.807489208695402, 50.183884459666544 ] } },
{ "type": "Feature", "properties": { }, "geometry": { "type": "Point", "coordinates": [ 1.814149348085009, 50.118666119808964 ] } },
{ "type": "Feature", "properties": { }, "geometry": { "type": "Point", "coordinates": [ 1.770201707018073, 50.112298728613993 ] } },
{ "type": "Feature", "properties": { }, "geometry": { "type": "Point", "coordinates": [ 1.645656916469097, 50.129453267423834 ] } },
{ "type": "Feature", "properties": { }, "geometry": { "type": "Point", "coordinates": [ 1.555658549308601, 50.083582104277042 ] } },
{ "type": "Feature", "properties": { }, "geometry": { "type": "Point", "coordinates": [ 1.743841256025002, 50.058613367057795 ] } },
{ "type": "Feature", "properties": { }, "geometry": { "type": "Point", "coordinates": [ 1.651915423458262, 50.125565334433148 ] } },
{ "type": "Feature", "properties": { }, "geometry": { "type": "Point", "coordinates": [ 1.640546718980822, 50.128737347863769 ] } },
{ "type": "Feature", "properties": { }, "geometry": { "type": "Point", "coordinates": [ 1.648663423380861, 50.132124229423241 ] } },
{ "type": "Feature", "properties": { }, "geometry": { "type": "Point", "coordinates": [ 1.765075450661802, 50.1122472761393 ] } },
{ "type": "Feature", "properties": { }, "geometry": { "type": "Point", "coordinates": [ 1.774350465151401, 50.110361829054689 ] } },
{ "type": "Feature", "properties": { }, "geometry": { "type": "Point", "coordinates": [ 1.774270887115082, 50.113658338624489 ] } },
{ "type": "Feature", "properties": { }, "geometry": { "type": "Point", "coordinates": [ 1.765988534922911, 50.116872674237463 ] } },
{ "type": "Feature", "properties": { }, "geometry": { "type": "Point", "coordinates": [ 1.957514591240031, 50.179313427302858 ] } },
{ "type": "Feature", "properties": { }, "geometry": { "type": "Point", "coordinates": [ 1.922310976034626, 50.144721135667815 ] } },
{ "type": "Feature", "properties": { }, "geometry": { "type": "Point", "coordinates": [ 1.895780379318525, 50.232183035344519 ] } },
{ "type": "Feature", "properties": { }, "geometry": { "type": "Point", "coordinates": [ 1.953448847905364, 50.177300743603183 ] } },
{ "type": "Feature", "properties": { }, "geometry": { "type": "Point", "coordinates": [ 1.959567876527042, 50.17933081880004 ] } },
{ "type": "Feature", "properties": { }, "geometry": { "type": "Point", "coordinates": [ 1.963795709812577, 50.173432080308025 ] } },
{ "type": "Feature", "properties": { }, "geometry": { "type": "Point", "coordinates": [ 1.960648576006229, 50.176702433784115 ] } },
{ "type": "Feature", "properties": { }, "geometry": { "type": "Point", "coordinates": [ 1.958649554210867, 50.174047983964833 ] } },
{ "type": "Feature", "properties": { }, "geometry": { "type": "Point", "coordinates": [ 1.823558485794295, 50.138622256793845 ] } },
{ "type": "Feature", "properties": { }, "geometry": { "type": "Point", "coordinates": [ 1.823568038330417, 50.138210203431079 ] } },
{ "type": "Feature", "properties": { }, "geometry": { "type": "Point", "coordinates": [ 1.82472204819926, 50.138221249081063 ] } },
{ "type": "Feature", "properties": { }, "geometry": { "type": "Point", "coordinates": [ 1.824073292857684, 50.138544756684979 ] } }
]
}
